surrortg_sdk.py
surrortg_sdk-0.0.1a1.dist-info/WHEEL
surrortg_sdk-0.0.1a1.dist-info/METADATA
surrortg_sdk-0.0.1a1.dist-info/RECORD
