Metadata-Version: 2.1
Name: surrortg_sdk
Version: 0.0.1a1
Summary: surrortg_sdk
Home-page: https://github.com/SurrogateInc/surrortgsdk-sdk
License: UNKNOWN
Author: Surrogate Inc
Classifier: License :: OSI Approved :: MIT License
